Metadata-Version: 2.1
Name: zswiss
Version: 0.1.0
Summary: some tools, simple but useful
Author: neilxzhang
Author-email: legend_zhx@163.com
License: MIT License
Platform: all
Classifier: Intended Audience :: Developers
Classifier: Operating System :: OS Independent
Classifier: Natural Language :: Chinese (Simplified)
Classifier: Programming Language :: Python
Classifier: Programming Language :: Python :: 2
Classifier: Programming Language :: Python :: 2.7
Classifier: Programming Language :: Python :: 3
Classifier: Programming Language :: Python :: 3.5
Classifier: Programming Language :: Python :: 3.6
Classifier: Programming Language :: Python :: 3.7
Classifier: Programming Language :: Python :: 3.8
Classifier: Programming Language :: Python :: 3.9
Classifier: Topic :: Software Development :: Libraries
License-File: LICENSE
